search_pkg/__init__.py
search_pkg/search_base.py
tests/__init__.py
tests/binary_search_test.py
tests/linear_search_test.py
tests/ternary_search_test.py
tests/two_dimensional_search.py
AniDSAKit-0.1.0.dist-info/METADATA
AniDSAKit-0.1.0.dist-info/WHEEL
AniDSAKit-0.1.0.dist-info/top_level.txt
AniDSAKit-0.1.0.dist-info/RECORD
