Metadata-Version: 2.1
Name: AniDSAKit
Version: 0.1.0
Summary: This DSAkit package contains searching algorithm
Home-page: https://github.com/Anirudhrarao/DSAkit
Author: Anirudhra rao
Author-email: raorudhra16@gmail.com
Classifier: Programming Language :: Python :: 3
Classifier: License :: OSI Approved :: MIT License
Classifier: Operating System :: OS Independent
Requires-Python: >=3.6
